{
  "name": "Infinity Realms Adventure",
  "description": "In the world of Infinity Realms Adventure, the higher the category of NFTs, the more generous the $INFT token reward for holding them, opening up an endless stream of rewards.",
  "social_links": [
    "https://t.me/TokenInfinity",
    "https://t.me/TokenInfinityChat",
    "https://t.me/InfinityNFTBot"
  ],
  "image": "https://github.com/Danil1110/NFTcollcetion/blob/6542331ba553f4ae55f7a75309aec29a5d64d370/CollcetionLogoNFT.jpg",
  "cover_image": "https://github.com/Danil1110/NFTcollcetion/blob/6542331ba553f4ae55f7a75309aec29a5d64d370/CollectionBanner.jpg"
}
